zar_shansi/__init__.py
zar_shansi/zar.py
zar_shansi-0.1.0.dist-info/LICENSE
zar_shansi-0.1.0.dist-info/METADATA
zar_shansi-0.1.0.dist-info/WHEEL
zar_shansi-0.1.0.dist-info/RECORD
