Metadata-Version: 2.3
Name: zar-shansi
Version: 0.1.0
Summary: 
Author: Atilla
Requires-Python: >=3.12
Classifier: Programming Language :: Python :: 3
Classifier: Programming Language :: Python :: 3.12
Classifier: Programming Language :: Python :: 3.13
